tests/__init__.py
tests/v2/__init__.py
tests/v2/bad_plugins.py
tests/v2/cluster.py
tests/v2/console.py
tests/v2/definitions.py
tests/v2/down.py
tests/v2/extract.py
tests/v2/generate_ansible.py
tests/v2/generate_nso.py
tests/v2/generate_pyats.py
tests/v2/good_plugins.py
tests/v2/groups.py
tests/v2/id.py
tests/v2/ls.py
tests/v2/nodes.py
tests/v2/pull.py
tests/v2/rm.py
tests/v2/save.py
tests/v2/search.py
tests/v2/ssh.py
tests/v2/start.py
tests/v2/stop.py
tests/v2/telnet.py
tests/v2/test_cli.py
tests/v2/tmux.py
tests/v2/up.py
tests/v2/use.py
tests/v2/users.py
tests/v2/wipe.py
tests/v2/mocks/__init__.py
tests/v2/mocks/api.py
tests/v2/mocks/github.py
tests/v2/mocks/nso.py
virl/__init__.py
virl/about.py
virl/helpers.py
virl/api/__init__.py
virl/api/api.py
virl/api/cml.py
virl/api/credentials.py
virl/api/github.py
virl/api/nso.py
virl/api/plugin.py
virl/cli/__init__.py
virl/cli/main.py
virl/cli/clear/__init__.py
virl/cli/clear/commands.py
virl/cli/cluster/__init__.py
virl/cli/cluster/info/__init__.py
virl/cli/cluster/info/commands.py
virl/cli/cockpit/__init__.py
virl/cli/cockpit/commands.py
virl/cli/command/__init__.py
virl/cli/command/commands.py
virl/cli/console/__init__.py
virl/cli/console/commands.py
virl/cli/definitions/__init__.py
virl/cli/definitions/images/__init__.py
virl/cli/definitions/images/export/__init__.py
virl/cli/definitions/images/export/commands.py
virl/cli/definitions/images/iimport/__init__.py
virl/cli/definitions/images/iimport/definition/__init__.py
virl/cli/definitions/images/iimport/definition/commands.py
virl/cli/definitions/images/iimport/image_file/__init__.py
virl/cli/definitions/images/iimport/image_file/commands.py
virl/cli/definitions/images/ls/__init__.py
virl/cli/definitions/images/ls/commands.py
virl/cli/definitions/nodes/__init__.py
virl/cli/definitions/nodes/export/__init__.py
virl/cli/definitions/nodes/export/commands.py
virl/cli/definitions/nodes/ls/__init__.py
virl/cli/definitions/nodes/ls/commands.py
virlutils-2.5.0.dist-info/licenses/LICENSE
virlutils-2.5.0.dist-info/METADATA
virlutils-2.5.0.dist-info/WHEEL
virlutils-2.5.0.dist-info/entry_points.txt
virlutils-2.5.0.dist-info/top_level.txt
virlutils-2.5.0.dist-info/RECORD
