Metadata-Version: 2.4
Name: virlutils
Version: 2.5.0
Summary: A collection of utilities for interacting with Cisco Modeling Labs
Home-page: https://github.com/CiscoDevNet/virlutils
Author: Joe Clarke
Author-email: jclarke@cisco.com
Classifier: Programming Language :: Python :: 3
Classifier: License :: OSI Approved :: MIT License
Classifier: Operating System :: OS Independent
Requires-Python: >=3.8
License-File: LICENSE
Requires-Dist: PyYAML
Requires-Dist: click
Requires-Dist: jinja2
Requires-Dist: libtmux>=0.34.0
Requires-Dist: requests
Requires-Dist: tabulate
Requires-Dist: virl2-client>=2.7.0
Dynamic: author
Dynamic: author-email
Dynamic: classifier
Dynamic: description
Dynamic: description-content-type
Dynamic: home-page
Dynamic: license-file
Dynamic: requires-dist
Dynamic: requires-python
Dynamic: summary
